audiospotter_cli/__init__.py
audiospotter_cli/cli.py
audiospotter_cli/client.py
audiospotter_cli/config.py
audiospotter_cli/sources.py
audiospotter_cli/utils.py
audiospotter_cli-0.2.dist-info/LICENSE
audiospotter_cli-0.2.dist-info/METADATA
audiospotter_cli-0.2.dist-info/WHEEL
audiospotter_cli-0.2.dist-info/entry_points.txt
audiospotter_cli-0.2.dist-info/top_level.txt
audiospotter_cli-0.2.dist-info/RECORD
