Metadata-Version: 2.1
Name: audiospotter-cli
Version: 0.2
Summary: A command-line tool for initializing projects and uploading audio to AudioSpotter API servers
Author-email: Joe Weiss <joe.weiss@gmail.com>
Project-URL: Homepage, https://github.com/joeweiss/audiospotter-cli
Project-URL: Bug Tracker, https://github.com/joeweiss/audiospotter-cli/issues
Requires-Python: >=3.8
License-File: LICENSE
Requires-Dist: cachetools
Requires-Dist: requests
Requires-Dist: rich
Requires-Dist: boto3
Requires-Dist: click
Requires-Dist: uplink
Requires-Dist: PyYAML
Requires-Dist: wavinfo
